audiomerger/__init__.py
audiomerger-0.1.0.dist-info/licenses/LICENSE
audiomerger-0.1.0.dist-info/METADATA
audiomerger-0.1.0.dist-info/WHEEL
audiomerger-0.1.0.dist-info/top_level.txt
audiomerger-0.1.0.dist-info/RECORD
