Metadata-Version: 2.4
Name: audiomerger
Version: 0.1.0
Summary: A simple package to merge audio files using base64 encoding
Home-page: https://github.com/guiconti/audiomerger
Author: Guilherme Conti Teixeira
Author-email: guibasconti@gmail.com
Classifier: Programming Language :: Python :: 3
Classifier: Operating System :: OS Independent
Requires-Python: >=3.6
License-File: LICENSE
Requires-Dist: requests>=2.25.0
Dynamic: author
Dynamic: author-email
Dynamic: classifier
Dynamic: description
Dynamic: description-content-type
Dynamic: home-page
Dynamic: license-file
Dynamic: requires-dist
Dynamic: requires-python
Dynamic: summary
